norm_toolkit/__init__.py
norm_toolkit/build_merged.py
norm_toolkit/build_ontology.py
norm_toolkit/build_umls.py
norm_toolkit/constants.py
norm_toolkit/models.py
norm_toolkit/normalizer.py
norm_toolkit/normalizer_cache.py
norm_toolkit/normalizer_postgres.py
norm_toolkit/normalizer_utils.py
norm_toolkit/utils.py
norm_toolkit-1.7.0.dist-info/WHEEL
norm_toolkit-1.7.0.dist-info/METADATA
norm_toolkit-1.7.0.dist-info/RECORD
