Metadata-Version: 2.3
Name: norm_toolkit
Version: 1.7.0
Summary: Toolkit to normalize text to UMLS / ontologies
Author: Haydn Jones
Author-email: Haydn Jones <haydnjonest@gmail.com>
Requires-Dist: asyncpg>=0.29.0
Requires-Dist: duckdb>=1.4.3
Requires-Dist: lvg-norm>=1.1.0
Requires-Dist: polars[rt64]>=1.36.1
Requires-Dist: pyarrow>=20.0.0
Requires-Dist: pydantic>=2.12.5
Requires-Dist: sqlalchemy>=2.0.0
Requires-Dist: tqdm>=4.67.1
Requires-Python: >=3.12
